[{"line":2,"elements":[{"start_timestamp":"2022-08-12T21:13:59.111Z","before":[{"result":{"duration":7685000,"status":"passed"},"match":{"location":"Hooks.Hooks.setUp()"}}],"line":15,"name":"put request roomlar icin","description":"","id":"room-get;put-request-roomlar-icin","after":[{"result":{"duration":11096000,"status":"passed"},"match":{"location":"Hooks.Hooks.tearDown(io.cucumber.java.Scenario)"}}],"type":"scenario","keyword":"Scenario","steps":[{"result":{"duration":891000,"status":"passed"},"line":16,"name":"kullanici roomlar icin put request yapar","match":{"location":"stepdefinitions.apiSteps.RoomApiGet.kullanici_roomlar_icin_put_request_yapar()"},"keyword":"Given "},{"result":{"status":"undefined"},"line":17,"name":"kullanici put request validation yapar","match":{},"keyword":"Then "}],"tags":[{"name":"@RoomApi"},{"name":"@PutRequest"}]}],"name":"Room get","description":"","id":"room-get","keyword":"Feature","uri":"file:src/test/resources/features/apiFeatures/RoomGet.feature","tags":[{"name":"@RoomApi","type":"Tag","location":{"line":1,"column":1}}]}]